verilog/ALUTangTest/logicUnit.v
module logicUnit (
    input [2:0] opCode,
    input [3:0] A, B,
    output [3:0] resultA, resultO, resultX
);

wire [3:0] and1, or1, xor1;

and a01 (and1[0], A[0], B[0]);
and a02 (and1[1], A[1], B[1]);
and a03 (and1[2], A[2], B[2]);
and a04 (and1[3], A[3], B[3]);

or o01 (or1[0], A[0], B[0]);
or o02 (or1[1], A[1], B[1]);
or o03 (or1[2], A[2], B[2]);
or o04 (or1[3], A[3], B[3]);

xor xor01 (xor1[0], A[0], B[0]);
xor xor02 (xor1[1], A[1], B[1]);
xor xor03 (xor1[2], A[2], B[2]);
xor xor04 (xor1[3], A[3], B[3]);

and a_o1 (resultA[0], opCode[0], and1[0]);
and a_o2 (resultA[1], opCode[0], and1[1]);
and a_o3 (resultA[2], opCode[0], and1[2]);
and a_o4 (resultA[3], opCode[0], and1[3]);

and o_o1 (resultO[0], opCode[1], or1[0]);
and o_o2 (resultO[1], opCode[1], or1[1]);
and o_o3 (resultO[2], opCode[1], or1[2]);
and o_o4 (resultO[3], opCode[1], or1[3]);

and x_o1 (resultX[0], opCode[2], xor1[0]);
and x_o2 (resultX[1], opCode[2], xor1[1]);
and x_o3 (resultX[2], opCode[2], xor1[2]);
and x_o4 (resultX[3], opCode[2], xor1[3]);

endmodule

verilog/ALU0.2/logicUnitTB.v
module logicUnitTB ();

reg [2:0] opCode;
reg [3:0] A, B;
wire [3:0] resultA, resultO, resultX;

logicUnit uut (
    .opCode(opCode),
    .A(A),
    .B(B),
    .resultA(resultA),
    .resultO(resultO),
    .resultX(resultX)
);

initial begin
    $dumpfile("logicUnit.vcd");
    $dumpvars;
    opCode = 3'b001; A = 4'b0001; B = 4'b0001; #2;
    opCode = 3'b001; A = 4'b0011; B = 4'b0001; #2;
    opCode = 3'b001; A = 4'b1001; B = 4'b1001; #2;
    opCode = 3'b001; A = 4'b1111; B = 4'b1111; #2;
    opCode = 3'b001; A = 4'b0000; B = 4'b0000; #2;

    opCode = 3'b010; A = 4'b0001; B = 4'b0101; #2;
    opCode = 3'b010; A = 4'b1001; B = 4'b0101; #2;
    opCode = 3'b010; A = 4'b0001; B = 4'b1111; #2;
    opCode = 3'b010; A = 4'b0000; B = 4'b0101; #2;

    opCode = 3'b100; A = 4'b0000; B = 4'b0101; #2;
    opCode = 3'b100; A = 4'b0000; B = 4'b0000; #2;
    opCode = 3'b100; A = 4'b0000; B = 4'b0101; #2;
    opCode = 3'b100; A = 4'b1111; B = 4'b1111; #2;
    $finish;
end

endmodule

verilog/ALU0.2/logicUnit.vcd
$date
	Sat Dec 14 03:32:40 2024
$end
$version
	Icarus Verilog
$end
$timescale
	1s
$end
$scope module logicUnitTB $end
$var wire 4 ! resultX [3:0] $end
$var wire 4 " resultO [3:0] $end
$var wire 4 # resultA [3:0] $end
$var reg 4 $ A [3:0] $end
$var reg 4 % B [3:0] $end
$var reg 3 & opCode [2:0] $end
$scope module uut $end
$var wire 4 ' A [3:0] $end
$var wire 4 ( B [3:0] $end
$var wire 3 ) opCode [2:0] $end
$var wire 4 * xor1 [3:0] $end
$var wire 4 + resultX [3:0] $end
$var wire 4 , resultO [3:0] $end
$var wire 4 - resultA [3:0] $end
$var wire 4 . or1 [3:0] $end
$var wire 4 / and1 [3:0] $end
$upscope $end
$upscope $end
$enddefinitions $end
#0
$dumpvars
b1 /
b1 .
b1 -
b0 ,
b0 +
b0 *
b1 )
b1 (
b1 '
b1 &
b1 %
b1 $
b1 #
b0 "
b0 !
$end
#2
b11 .
b10 *
b11 $
b11 '
#4
b1001 #
b1001 -
b1001 /
b1001 .
b0 *
b1001 %
b1001 (
b1001 $
b1001 '
#6
b1111 #
b1111 -
b1111 /
b1111 .
b1111 %
b1111 (
b1111 $
b1111 '
#8
b0 #
b0 -
b0 /
b0 .
b0 %
b0 (
b0 $
b0 '
#10
b101 "
b101 ,
b100 *
b1 /
b101 .
b101 %
b101 (
b1 $
b1 '
b10 &
b10 )
#12
b1101 "
b1101 ,
b1101 .
b1100 *
b1001 $
b1001 '
#14
b1111 "
b1111 ,
b1111 .
b1110 *
b1111 %
b1111 (
b1 $
b1 '
#16
b101 "
b101 ,
b101 .
b0 /
b101 *
b101 %
b101 (
b0 $
b0 '
#18
b0 "
b0 ,
b101 !
b101 +
b100 &
b100 )
#20
b0 !
b0 +
b0 .
b0 *
b0 %
b0 (
#22
b101 !
b101 +
b101 .
b101 *
b101 %
b101 (
#24
b0 !
b0 +
b1111 /
b1111 .
b0 *
b1111 %
b1111 (
b1111 $
b1111 '
