verilog/ALU0.2/opCode.v
module opCode (
    input [2:0] A,
    output [7:0] opCode
);
    wire and1, and2, and3, and4, notA, notB, notC;

    not n1(notA, A[2]);
    not n2(notB, A[1]);
    not n3(notC, A[0]);

    and a01(and1, A[2], A[1]);
    and a02(and2, notA, A[1]);
    and a03(and3, A[2], notB);
    and a04(and4, notA, notB);

    and a1(opCode[0], and4, notC);
    and a2(opCode[1], and4, A[0]);
    and a3(opCode[2], and2, notC);
    and a4(opCode[3], and2, A[0]);
    and a5(opCode[4], and3, notC);
    and a6(opCode[5], and3, A[0]);
    and a7(opCode[6], and1, notC);
    and a8(opCode[7], and1, A[0]);

endmodule

verilog/ALU0.2/opCodeTB.v
module opCodeTB();

reg [2:0] A;
wire [7:0] opCode;

opCode uut (
    .A(A),

    .opCode(opCode)
);

initial begin
    $dumpfile("opCode.vcd");
    $dumpvars;
    A = 3'b000; #3;
    A = 3'b001; #3;
    A = 3'b010; #3;
    A = 3'b011; #3;
    A = 3'b100; #3;
    A = 3'b101; #3;
    A = 3'b110; #3;
    A = 3'b111; #3;
    $finish;
end

endmodule

verilog/ALU0.2/opCode.vcd
$date
	Sun Dec 15 04:12:35 2024
$end
$version
	Icarus Verilog
$end
$timescale
	1s
$end
$scope module opCodeTB $end
$var wire 8 ! opCode [7:0] $end
$var reg 3 " A [2:0] $end
$scope module uut $end
$var wire 3 # A [2:0] $end
$var wire 1 $ and1 $end
$var wire 1 % and2 $end
$var wire 1 & and3 $end
$var wire 1 ' and4 $end
$var wire 1 ( notA $end
$var wire 1 ) notB $end
$var wire 1 * notC $end
$var wire 8 + opCode [7:0] $end
$upscope $end
$upscope $end
$enddefinitions $end
#0
$dumpvars
b1 +
1*
1)
1(
1'
0&
0%
0$
b0 #
b0 "
b1 !
$end
#3
0*
b10 !
b10 +
b1 "
b1 #
#6
0'
0)
1*
1%
b100 !
b100 +
b10 "
b10 #
#9
0*
b1000 !
b1000 +
b11 "
b11 #
#12
1&
0(
1)
1*
0%
b10000 !
b10000 +
b100 "
b100 #
#15
0*
b100000 !
b100000 +
b101 "
b101 #
#18
0&
0)
1*
1$
b1000000 !
b1000000 +
b110 "
b110 #
#21
0*
b10000000 !
b10000000 +
b111 "
b111 #
